baseai/__init__.py
baseai/agent.py
baseai/baseai_client.py
baseai/models.py
baseai/thread.py
baseai/tools.py
baseai/api/__init__.py
baseai/api/agents.py
baseai/api/threads.py
baseai/api/utils.py
a2abase_sdk-1.0.4.dist-info/METADATA
a2abase_sdk-1.0.4.dist-info/WHEEL
a2abase_sdk-1.0.4.dist-info/top_level.txt
a2abase_sdk-1.0.4.dist-info/RECORD
