Metadata-Version: 2.4
Name: a2abase-sdk
Version: 1.0.4
Summary: Official Python SDK for building powerful AI agents with access to 50+ built-in tools, 300+ integrations, and all major LLMs—all through a single, unified platform.
Author-email: BelArabyAI <mk@belaraby.com>
License: MIT
Project-URL: Homepage, https://github.com/A2ABaseAI/sdks
Project-URL: Documentation, https://github.com/A2ABaseAI/sdks
Project-URL: Repository, https://github.com/A2ABaseAI/sdks.git
Project-URL: Issues, https://github.com/A2ABaseAI/sdks/issues
Project-URL: Support, https://discord.gg/qAncfHmYUm
Keywords: baseai,ai,sdk,python,agent,llm
Classifier: Development Status :: 4 - Beta
Classifier: Intended Audience :: Developers
Classifier: License :: OSI Approved :: MIT License
Classifier: Programming Language :: Python :: 3
Classifier: Programming Language :: Python :: 3.11
Classifier: Programming Language :: Python :: 3.12
Classifier: Topic :: Software Development :: Libraries :: Python Modules
Requires-Python: >=3.11
Requires-Dist: httpx>=0.28.1
Requires-Dist: fastmcp>=2.10.6
